openk4a/__init__.py
openk4a/calibration.py
openk4a/capture.py
openk4a/playback.py
openk4a/stream.py
openk4a/transform.py
openk4a/types.py
openk4a/utils/__init__.py
openk4a/utils/_calibration_utils.py
tests/__init__.py
tests/test_distortion_mapping.py
tests/test_utils.py
open_azure_kinect-0.1.0.dist-info/LICENSE
open_azure_kinect-0.1.0.dist-info/METADATA
open_azure_kinect-0.1.0.dist-info/WHEEL
open_azure_kinect-0.1.0.dist-info/top_level.txt
open_azure_kinect-0.1.0.dist-info/RECORD
