Metadata-Version: 2.1
Name: open-azure-kinect
Version: 0.1.0
Summary: Cross-platform playback library for Microsoft Azure Kinect MKV files.
Home-page: https://github.com/cansik/open-azure-kinect
Author: Florian Bruggisser
Author-email: github@broox.ch
License: GPL-2.0 License
License-File: LICENSE
Requires-Dist: ffmpegio~=0.11.1
Requires-Dist: numpy
Requires-Dist: opencv-python
